metaprinter/__init__.py
metaprinter/core.py
metaprinter-0.2.7.dist-info/WHEEL
metaprinter-0.2.7.dist-info/entry_points.txt
metaprinter-0.2.7.dist-info/METADATA
metaprinter-0.2.7.dist-info/RECORD
