Metadata-Version: 2.4
Name: metaprinter
Version: 0.2.7
Summary: print and extract spss metadata
Author: Albert Li
License-Expression: MIT
Requires-Dist: pandas>=2.3.0
Requires-Dist: polars>=1.3.0
Requires-Dist: pyreadstat>=1.3.0
Requires-Python: >=3.11
